pycentral/__init__.py
pycentral/audit_logs.py
pycentral/base.py
pycentral/base_utils.py
pycentral/configuration.py
pycentral/constants.py
pycentral/exception.py
pycentral/firmware_management.py
pycentral/licensing.py
pycentral/monitoring.py
pycentral/rapids.py
pycentral/refresh_api_token.py
pycentral/topology.py
pycentral/url_utils.py
pycentral/user_management.py
pycentral/visualrf.py
pycentral/workflows/__init__.py
pycentral/workflows/config_apsettings_from_csv.py
pycentral/workflows/workflows_utils.py
opsdis_pycentral-0.0.4.dist-info/LICENSE
opsdis_pycentral-0.0.4.dist-info/METADATA
opsdis_pycentral-0.0.4.dist-info/WHEEL
opsdis_pycentral-0.0.4.dist-info/top_level.txt
opsdis_pycentral-0.0.4.dist-info/RECORD
