Metadata-Version: 2.1
Name: opsdis-pycentral
Version: 0.0.4
Summary: Aruba Central Python Package, with changes by opsdis waiting for pull #12 to be merge
Home-page: https://github.com/aruba/pycentral
Author: aruba-automation
Author-email: aruba-automation@hpe.com
License: UNKNOWN
Platform: UNKNOWN
Classifier: Programming Language :: Python :: 3 :: Only
Classifier: License :: OSI Approved :: MIT License
Classifier: Operating System :: OS Independent
Classifier: Intended Audience :: System Administrators
Classifier: Topic :: System :: Networking
Classifier: Development Status :: 4 - Beta
Requires-Python: >=3.6
License-File: LICENSE
Requires-Dist: requests
Requires-Dist: PyYAML
Requires-Dist: urllib3
Requires-Dist: certifi
Provides-Extra: colorlog
Requires-Dist: colorlog ; extra == 'colorlog'
